topsis/__init__.py
topsis/topsis.py
Topsis_Ayush_102203119-1.0.2.dist-info/LICENSE
Topsis_Ayush_102203119-1.0.2.dist-info/METADATA
Topsis_Ayush_102203119-1.0.2.dist-info/WHEEL
Topsis_Ayush_102203119-1.0.2.dist-info/entry_points.txt
Topsis_Ayush_102203119-1.0.2.dist-info/top_level.txt
Topsis_Ayush_102203119-1.0.2.dist-info/RECORD
