Metadata-Version: 2.2
Name: Topsis-Ayush-102203119
Version: 1.0.2
Summary: A Python package for implementing TOPSIS
Home-page: https://github.com/Ayush0126/Topsis-102203119
Author: Ayush Panwar
Author-email: apanwar_be22@thapar.edu
Classifier: Programming Language :: Python :: 3
Classifier: License :: OSI Approved :: MIT License
License-File: LICENSE
Requires-Dist: numpy
Requires-Dist: pandas
Dynamic: author
Dynamic: author-email
Dynamic: classifier
Dynamic: description
Dynamic: description-content-type
Dynamic: home-page
Dynamic: requires-dist
Dynamic: summary
